firetool.py
firetool-0.61.dist-info/DESCRIPTION.rst
firetool-0.61.dist-info/METADATA
firetool-0.61.dist-info/RECORD
firetool-0.61.dist-info/WHEEL
firetool-0.61.dist-info/entry_points.txt
firetool-0.61.dist-info/metadata.json
firetool-0.61.dist-info/top_level.txt
firetool_commands/__init__.py
firetool_commands/auth.py
firetool_commands/base_root_core.py
firetool_commands/common.py
firetool_commands/configstore.py
firetool_commands/git_credentials.py
firetool_commands/operations.py
