Metadata-Version: 2.0
Name: firetool
Version: 0.61
Summary: UNKNOWN
Home-page: UNKNOWN
Author: UNKNOWN
Author-email: UNKNOWN
License: UNKNOWN
Platform: UNKNOWN
Requires-Dist: click
Requires-Dist: gevent
Requires-Dist: oauth2client
Requires-Dist: requests
